Metadata-Version: 2.1
Name: astroNN
Version: 1.1.0
Summary: Deep Learning for Astronomers with Tensorflow
Home-page: https://github.com/henrysky/astroNN
Author: Henry Leung
Author-email: henrysky.leung@utoronto.ca
License: MIT
Project-URL: Bug Tracker, https://github.com/henrysky/astroNN/issues
Project-URL: Documentation, http://astronn.readthedocs.io/
Project-URL: Source Code, https://github.com/henrysky/astroNN
Classifier: Development Status :: 4 - Beta
Classifier: License :: OSI Approved :: MIT License
Classifier: Programming Language :: Python :: 3.8
Classifier: Intended Audience :: Science/Research
Classifier: Topic :: Scientific/Engineering :: Artificial Intelligence
Classifier: Topic :: Scientific/Engineering :: Astronomy
Requires-Python: >=3.8
License-File: LICENSE
Requires-Dist: numpy
Requires-Dist: astropy
Requires-Dist: h5py
Requires-Dist: matplotlib
Requires-Dist: astroquery
Requires-Dist: pandas
Requires-Dist: scikit-learn
Requires-Dist: tqdm
Requires-Dist: packaging
Requires-Dist: tensorflow (>=2.11.0)
Requires-Dist: tensorflow-probability (>=0.19.0)
